[
    {
        "id": 1,
        "name": "zus 1",
        "category": "zus",
        "link": "abc",
        "image": "http://formularze.iform.iform.pl/zdjecia/formularze/6425/1529481859zus-koa.jpg",
        "department": "ZUS",
        "year": 2018,
        "type": "wniosek",
        "description": "Opis - to jest opis wniosku"
    },
    {
        "id": 2,
        "name": "zus 2",
        "category": "zus",
        "link": "abc",
        "image": "http://formularze.iform.iform.pl/zdjecia/formularze/6425/1529481859zus-koa.jpg",
        "department": "ZUS",
        "year": 2018,
        "type": "wniosek",
        "description": "Opis - to jest opis wniosku"
    },
    {
        "id": 3,
        "name": "zus 3",
        "category": "zus",
        "link": "abc",
        "image": "http://formularze.iform.iform.pl/zdjecia/formularze/6425/1529481859zus-koa.jpg",
        "department": "ZUS",
        "year": 2018,
        "type": "wniosek",
        "description": "Opis - to jest opis wniosku"
    },
    {
        "id": 4,
        "name": "zus 4",
        "category": "zus",
        "link": "abc",
        "image": "http://formularze.iform.iform.pl/zdjecia/formularze/6425/1529481859zus-koa.jpg",
        "department": "ZUS",
        "year": 2018,
        "type": "wniosek",
        "description": "Opis - to jest opis wniosku"
    },
    {
        "id": 5,
        "name": "zus 5",
        "category": "zus",
        "link": "abc",
        "image": "http://formularze.iform.iform.pl/zdjecia/formularze/6425/1529481859zus-koa.jpg",
        "department": "ZUS",
        "year": 2018,
        "type": "wniosek",
        "description": "Opis - to jest opis wniosku"
    },
    {
        "id": 6,
        "name": "us 1",
        "category": "us",
        "link": "abc",
        "image": "http://formularze.iform.iform.pl/zdjecia/formularze/6425/1529481859zus-koa.jpg",
        "department": "urząd skarbowy",
        "year": 2018,
        "type": "wniosek",
        "description": "Opis - to jest opis wniosku"
    },
    {
        "id": 7,
        "name": "us 2",
        "category": "us",
        "link": "abc",
        "image": "http://formularze.iform.iform.pl/zdjecia/formularze/6425/1529481859zus-koa.jpg",
        "department": "urząd skarbowy",
        "year": 2018,
        "type": "wniosek",
        "description": "Opis - to jest opis wniosku"
    },
    {
        "id": 8,
        "name": "us 3",
        "category": "us",
        "link": "abc",
        "image": "http://formularze.iform.iform.pl/zdjecia/formularze/6425/1529481859zus-koa.jpg",
        "department": "urząd skarbowy",
        "year": 2018,
        "type": "wniosek",
        "description": "Opis - to jest opis wniosku"
    },
    {
        "id": 9,
        "name": "us 4",
        "category": "us",
        "link": "abc",
        "image": "http://formularze.iform.iform.pl/zdjecia/formularze/6425/1529481859zus-koa.jpg",
        "department": "urząd skarbowy",
        "year": 2018,
        "type": "wniosek",
        "description": "Opis - to jest opis wniosku"
    },
    {
        "id": 10,
        "name": "us 5",
        "category": "us",
        "link": "abc",
        "image": "http://formularze.iform.iform.pl/zdjecia/formularze/6425/1529481859zus-koa.jpg",
        "department": "urząd skarbowy",
        "year": 2018,
        "type": "wniosek",
        "description": "Opis - to jest opis wniosku"
    },
    {
        "id": 11,
        "name": "bank 1",
        "category": "bank",
        "link": "abc",
        "image": "http://formularze.iform.iform.pl/zdjecia/formularze/6425/1529481859zus-koa.jpg",
        "department": "Bank Polski",
        "year": 2018,
        "type": "wniosek",
        "description": "Opis - to jest opis wniosku"
    },
    {
        "id": 12,
        "name": "bank 2",
        "category": "bank",
        "link": "abc",
        "image": "http://formularze.iform.iform.pl/zdjecia/formularze/6425/1529481859zus-koa.jpg",
        "department": "Bank Polski",
        "year": 2018,
        "type": "wniosek",
        "description": "Opis - to jest opis wniosku"
    },
    {
        "id": 13,
        "name": "bank 3",
        "category": "bank",
        "link": "abc",
        "image": "http://formularze.iform.iform.pl/zdjecia/formularze/6425/1529481859zus-koa.jpg",
        "department": "Bank Polski",
        "year": 2018,
        "type": "wniosek",
        "description": "Opis - to jest opis wniosku"
    },
    {
        "id": 14,
        "name": "bank 4",
        "category": "bank",
        "link": "abc",
        "image": "http://formularze.iform.iform.pl/zdjecia/formularze/6425/1529481859zus-koa.jpg",
        "department": "Bank Polski",
        "year": 2018,
        "type": "wniosek",
        "description": "Opis - to jest opis wniosku"
    },
    {
        "id": 15,
        "name": "bank 5",
        "category": "bank",
        "link": "abc",
        "image": "http://formularze.iform.iform.pl/zdjecia/formularze/6425/1529481859zus-koa.jpg",
        "department": "Bank Polski",
        "year": 2018,
        "type": "wniosek",
        "description": "Opis - to jest opis wniosku"
    },
    {
        "id": 16,
        "name": "dg 1",
        "category": "dg",
        "link": "abc",
        "image": "http://formularze.iform.iform.pl/zdjecia/formularze/6425/1529481859zus-koa.jpg",
        "department": "urzad miasta",
        "year": 2018,
        "type": "wniosek",
        "description": "Opis - to jest opis wniosku"
    },
    {
        "id": 17,
        "name": "dg 2",
        "category": "dg",
        "link": "abc",
        "image": "http://formularze.iform.iform.pl/zdjecia/formularze/6425/1529481859zus-koa.jpg",
        "department": "urząd skarbowy",
        "year": 2018,
        "type": "wniosek",
        "description": "Opis - to jest opis wniosku"
    },
    {
        "id": 18,
        "name": "dg 3",
        "category": "dg",
        "link": "abc",
        "image": "http://formularze.iform.iform.pl/zdjecia/formularze/6425/1529481859zus-koa.jpg",
        "department": "ZUS",
        "year": 2018,
        "type": "wniosek",
        "description": "Opis - to jest opis wniosku"
    },
    {
        "id": 19,
        "name": "dg 4",
        "category": "dg",
        "link": "abc",
        "image": "http://formularze.iform.iform.pl/zdjecia/formularze/6425/1529481859zus-koa.jpg",
        "department": "ZUS",
        "year": 2018,
        "type": "wniosek",
        "description": "Opis - to jest opis wniosku"
    },
    {
        "id": 20,
        "name": "dg 5",
        "category": "dg",
        "link": "abc",
        "image": "http://formularze.iform.iform.pl/zdjecia/formularze/6425/1529481859zus-koa.jpg",
        "department": "urząd skarbowy",
        "year": 2018,
        "type": "wniosek",
        "description": "Opis - to jest opis wniosku"
    },
    {
        "id": 21,
        "name": "other 1",
        "category": "other",
        "link": "abc",
        "image": "http://formularze.iform.iform.pl/zdjecia/formularze/6425/1529481859zus-koa.jpg",
        "department": "ZUS",
        "year": 2018,
        "type": "wniosek",
        "description": "Opis - to jest opis wniosku"
    },
    {
        "id": 22,
        "name": "other 2",
        "category": "other",
        "link": "abc",
        "image": "http://formularze.iform.iform.pl/zdjecia/formularze/6425/1529481859zus-koa.jpg",
        "department": "ZUS",
        "year": 2018,
        "type": "wniosek",
        "description": "Opis - to jest opis wniosku"
    },
    {
        "id": 23,
        "name": "other 3",
        "category": "other",
        "link": "abc",
        "image": "http://formularze.iform.iform.pl/zdjecia/formularze/6425/1529481859zus-koa.jpg",
        "department": "urząd skarbowy",
        "year": 2018,
        "type": "wniosek",
        "description": "Opis - to jest opis wniosku"
    },
    {
        "id": 24,
        "name": "other 4",
        "category": "other",
        "link": "abc",
        "image": "http://formularze.iform.iform.pl/zdjecia/formularze/6425/1529481859zus-koa.jpg",
        "department": "urząd skarbowy",
        "year": 2018,
        "type": "wniosek",
        "description": "Opis - to jest opis wniosku"
    },
    {
        "id": 25,
        "name": "other 5",
        "category": "other",
        "link": "abc",
        "image": "http://formularze.iform.iform.pl/zdjecia/formularze/6425/1529481859zus-koa.jpg",
        "department": "bank",
        "year": 2018,
        "type": "wniosek",
        "description": "Opis - to jest opis wniosku"
    },
    {
        "id": 26,
        "name": "bank 6",
        "category": "other",
        "image": "http://formularze.iform.iform.pl/zdjecia/formularze/6425/1529481859zus-koa.jpg",
        "department": "bank",
        "year": 2018,
        "type": "wniosek",
        "description": "Opis - to jest opis wniosku"
    }
]